kudaf_datasource_tools/__init__.py
kudaf_datasource_tools/config/__init__.py
kudaf_datasource_tools/config/config_example.yaml
kudaf_datasource_tools/config/cookiecutter.json
kudaf_datasource_tools/config/logger.py
kudaf_datasource_tools/logic/__init__.py
kudaf_datasource_tools/logic/exceptions.py
kudaf_datasource_tools/logic/models.py
kudaf_datasource_tools/logic/process.py
kudaf_datasource_tools/logic/temporal_attributes.py
kudaf_datasource_tools/logic/unit_type_variables/FAMILIE.json
kudaf_datasource_tools/logic/unit_type_variables/FORETAK.json
kudaf_datasource_tools/logic/unit_type_variables/FYLKE.json
kudaf_datasource_tools/logic/unit_type_variables/FYLKESKOMMUNE.json
kudaf_datasource_tools/logic/unit_type_variables/HUSHOLDNING.json
kudaf_datasource_tools/logic/unit_type_variables/JOBB.json
kudaf_datasource_tools/logic/unit_type_variables/KJORETOY.json
kudaf_datasource_tools/logic/unit_type_variables/KOMMUNE.json
kudaf_datasource_tools/logic/unit_type_variables/KURS.json
kudaf_datasource_tools/logic/unit_type_variables/PERSON.json
kudaf_datasource_tools/logic/unit_type_variables/VIRKSOMHET.json
kudaf_datasource_tools/logic/unit_type_variables/__init__.py
kudaf_datasource_tools/logic/utils.py
kudaf_datasource_tools/main.py
kudaf_datasource_tools/template_api/__init__.py
kudaf_datasource_tools/template_api/cookiecutter.json
kudaf_datasource_tools/template_api/{{cookiecutter.module_name}}/.gitignore
kudaf_datasource_tools/template_api/{{cookiecutter.module_name}}/.gitlab-ci.yml
kudaf_datasource_tools/template_api/{{cookiecutter.module_name}}/Dockerfile
kudaf_datasource_tools/template_api/{{cookiecutter.module_name}}/README.md
kudaf_datasource_tools/template_api/{{cookiecutter.module_name}}/app/__init__.py
kudaf_datasource_tools/template_api/{{cookiecutter.module_name}}/app/api/__init__.py
kudaf_datasource_tools/template_api/{{cookiecutter.module_name}}/app/api/api.py
kudaf_datasource_tools/template_api/{{cookiecutter.module_name}}/app/api/endpoints/__init__.py
kudaf_datasource_tools-0.4.4.dist-info/LICENSE.md
kudaf_datasource_tools-0.4.4.dist-info/METADATA
kudaf_datasource_tools-0.4.4.dist-info/WHEEL
kudaf_datasource_tools-0.4.4.dist-info/entry_points.txt
kudaf_datasource_tools-0.4.4.dist-info/RECORD
