Metadata-Version: 2.1
Name: kudaf_datasource_tools
Version: 0.4.4
Summary: CLI tools for the creation of Kudaf Data Source components: 1) Variables Metadata, and 2) REST API Datasource back-end
Home-page: https://gitlab.sikt.no/kudaf/kudaf-datasource-tools
License: MIT
Author: Daniel Díguele, Senioringeniør, Sikt - Kunnskapssektorens tjenesteleverandør 
Author-email: daniel.diguele@sikt.no
Maintainer: Daniel Díguele, Senioringeniør, Sikt - Kunnskapssektorens tjenesteleverandør 
Maintainer-email: daniel.diguele@sikt.no
Requires-Python: >=3.9,<4.0
Classifier: Framework :: FastAPI
Classifier: License :: OSI Approved :: MIT License
Classifier: Operating System :: OS Independent
Classifier: Programming Language :: Python :: 3
Classifier: Programming Language :: Python :: 3.9
Classifier: Programming Language :: Python :: 3.10
Classifier: Programming Language :: Python :: 3.11
Classifier: Topic :: Utilities
Requires-Dist: cookiecutter (>=2.5.0,<3.0.0)
Requires-Dist: cryptography (>=41.0.1,<42.0.0)
Requires-Dist: fastapi (>=0.104.1,<0.105.0)
Requires-Dist: httpx (>=0.27.0,<0.28.0)
Requires-Dist: pandas (>=2.1.3,<3.0.0)
Requires-Dist: pyarrow (>=12.0.1,<13.0.0)
Requires-Dist: pydantic (>=1.10.9,<2.0.0)
Requires-Dist: pyjwt (>=2.8.0,<3.0.0)
Requires-Dist: ruamel-yaml (>=0.18.5,<0.19.0)
Requires-Dist: typer[all] (>=0.9.0,<0.10.0)
Project-URL: Repository, https://gitlab.sikt.no/kudaf/kudaf-datasource-tools
